CHANGES.rst
LICENSE
MANIFEST.in
README.rst
package.json
setup.py
armstrong/__init__.py
armstrong.core.arm_sections.egg-info/PKG-INFO
armstrong.core.arm_sections.egg-info/SOURCES.txt
armstrong.core.arm_sections.egg-info/dependency_links.txt
armstrong.core.arm_sections.egg-info/namespace_packages.txt
armstrong.core.arm_sections.egg-info/requires.txt
armstrong.core.arm_sections.egg-info/top_level.txt
armstrong/core/__init__.py
armstrong/core/arm_sections/__init__.py
armstrong/core/arm_sections/admin.py
armstrong/core/arm_sections/backends.py
armstrong/core/arm_sections/managers.py
armstrong/core/arm_sections/models.py
armstrong/core/arm_sections/utils.py
armstrong/core/arm_sections/views.py
armstrong/core/arm_sections/migrations/0001_initial.py
armstrong/core/arm_sections/migrations/__init__.py
armstrong/core/arm_sections/south_migrations/0001_initial.py
armstrong/core/arm_sections/south_migrations/0002_auto__chg_field_section_slug__add_unique_section_full_slug.py
armstrong/core/arm_sections/south_migrations/__init__.py
armstrong/core/arm_sections/templates/arm_sections/sections_menu.html
armstrong/core/arm_sections/templates/arm_sections/sections_menu_dj14.html
armstrong/core/arm_sections/templatetags/__init__.py
armstrong/core/arm_sections/templatetags/section_helpers.py