Metadata-Version: 1.1
Name: armstrong.core.arm-sections
Version: 1.6.0
Summary: Provides hierarchical taxonomy for content
Home-page: http://github.com/armstrong/armstrong.core.arm_sections/
Author: Bay Citizen & Texas Tribune
Author-email: dev@armstrongcms.org
License: UNKNOWN
Platform: UNKNOWN
Classifier: Development Status :: 5 - Production/Stable
Classifier: Environment :: Web Environment
Classifier: Framework :: Django
Classifier: Intended Audience :: Developers
Classifier: License :: OSI Approved :: Apache Software License
Classifier: Operating System :: OS Independent
Classifier: Programming Language :: Python
Classifier: Programming Language :: Python :: 2.6
Classifier: Programming Language :: Python :: 2.7
